ts2vg.libs/libstdc++-496613c0.so.6.0.32
ts2vg.libs/libgcc_s-a3a07607.so.1
ts2vg-1.2.4.dist-info/top_level.txt
ts2vg-1.2.4.dist-info/WHEEL
ts2vg-1.2.4.dist-info/entry_points.txt
ts2vg-1.2.4.dist-info/METADATA
ts2vg-1.2.4.dist-info/LICENSE
ts2vg-1.2.4.dist-info/RECORD
ts2vg/_version.py
ts2vg/__init__.py
ts2vg/cli.py
ts2vg/graph/summary.py
ts2vg/graph/horizontal.py
ts2vg/graph/_base.c
ts2vg/graph/_base.cpython-39-x86_64-linux-gnu.so
ts2vg/graph/_horizontal_penetrable.cpython-39-x86_64-linux-gnu.so
ts2vg/graph/_natural_penetrable.cpython-39-x86_64-linux-gnu.so
ts2vg/graph/_horizontal.cpython-39-x86_64-linux-gnu.so
ts2vg/graph/_natural_penetrable.c
ts2vg/graph/__init__.py
ts2vg/graph/natural.py
ts2vg/graph/base.py
ts2vg/graph/_natural.cpp
ts2vg/graph/_horizontal_penetrable.c
ts2vg/graph/_horizontal.cpp
ts2vg/graph/_natural.cpython-39-x86_64-linux-gnu.so
