Metadata-Version: 2.1
Name: ts2vg
Version: 1.2.4
Summary: Build visibility graphs from time series data.
Author-email: Carlos Bergillos <c.bergillos.v@gmail.com>
License: MIT License
Project-URL: Homepage, https://carlosbergillos.github.io/ts2vg
Project-URL: Documentation, https://carlosbergillos.github.io/ts2vg
Project-URL: Source Code, https://github.com/CarlosBergillos/ts2vg
Keywords: graph,network,visibility,time,series
Classifier: License :: OSI Approved :: MIT License
Classifier: Programming Language :: Python
Classifier: Programming Language :: Python :: 3
Classifier: Programming Language :: Python :: 3.9
Classifier: Programming Language :: Python :: 3.10
Classifier: Programming Language :: Python :: 3.11
Classifier: Programming Language :: Python :: 3.12
Classifier: Programming Language :: Cython
Classifier: Topic :: Software Development :: Libraries :: Python Modules
Classifier: Operating System :: OS Independent
Classifier: Topic :: Scientific/Engineering :: Information Analysis
Classifier: Topic :: Scientific/Engineering :: Mathematics
Classifier: Development Status :: 5 - Production/Stable
Classifier: Intended Audience :: Science/Research
Requires-Python: >=3.9
License-File: LICENSE
Requires-Dist: numpy >=1.24
Provides-Extra: tests
Requires-Dist: pytest ; extra == 'tests'
